eNlightSDK/__init__.py
eNlightSDK/enlight_cloud.py
eNlightSDK/classes/__init__.py
eNlightSDK/classes/caller.py
eNlightSDK/classes/set_projects.py
eNlightSDK/classes/vm.py
eNlightSDKdemo1-1.0.dist-info/METADATA
eNlightSDKdemo1-1.0.dist-info/WHEEL
eNlightSDKdemo1-1.0.dist-info/top_level.txt
eNlightSDKdemo1-1.0.dist-info/RECORD
