Metadata-Version: 2.1
Name: eNlightSDKdemo1
Version: 1.0
Summary: VM CRUDs
Author: Akshay Ghatol
Author-email: akshay.ghatol@esds.co.in
